wa_but_py/__init__.py
wa_but_py/defaults.py
wa_but_py/handlers/noise_handler.py
wa_but_py/handlers/socket_handler.py
wa_but_py/types/socket.py
wa_but_py/utils/exceptions/noise_handshake_exceptions.py
wa_but_py/utils/models/models.py
wa_but_py/waproto/WAProto.proto
wa_but_py/waproto/compile.sh
wa_but_py/waproto/generated/WAProto_pb2.py
wa_but_py/waproto/generated/WAProto_pb2.pyi
wa_but_py-0.0.1.dist-info/LICENSE
wa_but_py-0.0.1.dist-info/METADATA
wa_but_py-0.0.1.dist-info/WHEEL
wa_but_py-0.0.1.dist-info/RECORD
