Metadata-Version: 2.3
Name: wa-but-py
Version: 0.0.1
Summary: A Python library for interacting with WhatsApp Web (unofficial API).
License: Custom License
Keywords: WhatsApp,Web API,Automation
Author: Zaid
Author-email: zaidyoutub0@gmail.com
Requires-Python: >=3.9.2,<4.0
Classifier: License :: Other/Proprietary License
Classifier: Programming Language :: Python :: 3
Classifier: Programming Language :: Python :: 3.10
Classifier: Programming Language :: Python :: 3.11
Classifier: Programming Language :: Python :: 3.12
Classifier: Programming Language :: Python :: 3.13
Requires-Dist: attrs (==24.3.0)
Requires-Dist: certifi (==2024.12.14)
Requires-Dist: cffi (==1.17.1)
Requires-Dist: charset-normalizer (==3.4.1)
Requires-Dist: cryptography (==44.0.0)
Requires-Dist: h11 (==0.14.0)
Requires-Dist: idna (==3.10)
Requires-Dist: mypy-protobuf (==3.6.0)
Requires-Dist: outcome (==1.3.0.post0)
Requires-Dist: protobuf (==5.29.3)
Requires-Dist: pycparser (==2.22)
Requires-Dist: pysocks (==1.7.1)
Requires-Dist: requests (==2.32.3)
Requires-Dist: setuptools (==75.8.0)
Requires-Dist: sniffio (==1.3.1)
Requires-Dist: sortedcontainers (==2.4.0)
Requires-Dist: trio (==0.28.0)
Requires-Dist: trio-websocket (==0.11.1)
Requires-Dist: types-protobuf (==5.29.1.20241207)
Requires-Dist: types-pyyaml (==6.0.12.20241230)
Requires-Dist: typing-extensions (==4.12.2)
Requires-Dist: urllib3 (==2.3.0)
Requires-Dist: websocket-client (==1.8.0)
Requires-Dist: websockets (==14.1)
Requires-Dist: wsproto (==1.2.0)
Project-URL: Documentation, https://github.com/hacxk/wa-but-py
Project-URL: Homepage, https://github.com/hacxk/wa-but-py
Project-URL: Repository, https://github.com/hacxk/wa-but-py
